text2markdown_formatter/__init__.py
text2markdown_formatter/main.py
text2markdown_formatter/prompts.py
text2markdown_formatter-2025.12.21173214.dist-info/METADATA
text2markdown_formatter-2025.12.21173214.dist-info/WHEEL
text2markdown_formatter-2025.12.21173214.dist-info/top_level.txt
text2markdown_formatter-2025.12.21173214.dist-info/RECORD
