Metadata-Version: 2.4
Name: text2markdown-formatter
Version: 2025.12.21173214
Summary: A new package designed to transform unstructured text inputs into well-formatted Markdown content. This tool is particularly useful for users who need to convert raw text, such as notes, ideas, or dra
Author-email: text2markdown-formatter <hi@eugene.plus>
License: MIT
Project-URL: Homepage, https://github.com/chigwell/text2markdown-formatter
Requires-Python: >=3.9
Requires-Dist: langchain-llm7>=0.0.0
Requires-Dist: llmatch-messages>=0.0.0
Requires-Dist: langchain-core>=0.3.0
